smaf/__init__.py
smaf/smart_call/__init__.py
smaf/smart_call/prompts.py
smaf/smart_call/smart_call.py
smaf/utils/__init__.py
smaf/utils/execute_code_with_variables.py
smaf/utils/get_data_around_call.py
smaf/utils/logging.py
smaf-0.1.3.dist-info/METADATA
smaf-0.1.3.dist-info/WHEEL
smaf-0.1.3.dist-info/RECORD
