Metadata-Version: 2.1
Name: smaf
Version: 0.1.3
Summary: Smart, code-aware functions.
Author: Joaquín Ossandon
Author-email: jossandonstanke@gmail.com
Requires-Python: >=3.11,<4.0
Classifier: Programming Language :: Python :: 3
Classifier: Programming Language :: Python :: 3.11
Classifier: Programming Language :: Python :: 3.12
Requires-Dist: openai (>=1.47.0,<2.0.0)
Requires-Dist: pydantic (>=2.9.2,<3.0.0)
